[
  {
    "idx": 1,
    "t": "0:02:17",
    "s": 137,
    "end": 332,
    "name": "Samurai Heart",
    "artist": "SPYAIR",
    "lang": "ja",
    "dur": 191,
    "lrcId": 889899,
    "originalTitle": "サムライハート (Some Like It Hot!!)",
    "nameEn": "Samurai Heart"
  },
  {
    "idx": 2,
    "t": "0:05:32",
    "s": 332,
    "end": 574,
    "name": "Tsukiakari",
    "artist": "Mikito-P feat. Rib",
    "lang": "ja",
    "dur": 237,
    "lrcId": 9583028,
    "originalTitle": "月陽-ツキアカリ-",
    "nameEn": "Moonlight"
  },
  {
    "idx": 3,
    "t": "0:09:34",
    "s": 574,
    "end": 918,
    "name": "Kimi no Shiranai Monogatari",
    "artist": "supercell",
    "lang": "ja",
    "dur": 339,
    "lrcId": 889963,
    "originalTitle": "君の知らない物語",
    "nameEn": "The Story You Don't Know"
  },
  {
    "idx": 4,
    "t": "0:15:18",
    "s": 918,
    "end": 1142,
    "name": "Kaiju no Hanauta",
    "artist": "Vaundy",
    "lang": "ja",
    "dur": 223,
    "lrcId": 5206912,
    "originalTitle": "怪獣の花唄",
    "nameEn": "Monster's Flower Song"
  },
  {
    "idx": 5,
    "t": "0:19:02",
    "s": 1142,
    "end": 1424,
    "name": "Kaishin no Ichigeki",
    "artist": "RADWIMPS",
    "lang": "ja",
    "dur": 277,
    "lrcId": 2375868,
    "originalTitle": "会心の一撃",
    "nameEn": "Critical Hit"
  },
  {
    "idx": 6,
    "t": "0:23:44",
    "s": 1424,
    "end": 1679,
    "name": "Kanzen Kankaku Dreamer",
    "artist": "ONE OK ROCK",
    "lang": "ja",
    "dur": 253,
    "lrcId": 9641405,
    "originalTitle": "完全感覚Dreamer"
  },
  {
    "idx": 7,
    "t": "0:27:59",
    "s": 1679,
    "end": 1933,
    "name": "Kimi Shidai Ressha",
    "artist": "ONE OK ROCK",
    "lang": "ja",
    "dur": 255,
    "lrcId": 1012795,
    "originalTitle": "キミシダイ列車",
    "nameEn": "You're-Up-to-It Train"
  },
  {
    "idx": 8,
    "t": "0:32:13",
    "s": 1933,
    "end": 2227,
    "name": "REVIVER",
    "artist": "MY FIRST STORY",
    "lang": "ja",
    "dur": 327,
    "lrcId": 1052509
  },
  {
    "idx": 9,
    "t": "0:37:07",
    "s": 2227,
    "end": 2433,
    "name": "CHAINSAW BLOOD",
    "artist": "Vaundy",
    "lang": "ja",
    "dur": 201,
    "lrcId": 947731
  },
  {
    "idx": 10,
    "t": "0:40:33",
    "s": 2433,
    "end": 2659,
    "name": "DADA",
    "artist": "RADWIMPS",
    "lang": "ja",
    "dur": 229,
    "lrcId": 11357607
  },
  {
    "idx": 11,
    "t": "0:44:19",
    "s": 2659,
    "end": 2863,
    "name": "Hiten",
    "artist": "Ayase × R-指定",
    "lang": "ja",
    "dur": 184,
    "lrcId": 9732072,
    "originalTitle": "飛天",
    "nameEn": "Soaring Heavens"
  },
  {
    "idx": 12,
    "t": "0:47:43",
    "s": 2863,
    "end": 3047,
    "name": "The Autumn Song",
    "artist": "ELLEGARDEN",
    "lang": "en",
    "dur": 183,
    "lrcId": 27374253
  },
  {
    "idx": 13,
    "t": "0:50:47",
    "s": 3047,
    "end": 3247,
    "name": "After Dark",
    "artist": "ASIAN KUNG-FU GENERATION",
    "lang": "ja",
    "dur": 194,
    "lrcId": 3079358,
    "originalTitle": "アフターダーク"
  },
  {
    "idx": 14,
    "t": "0:54:07",
    "s": 3247,
    "end": 3468,
    "name": "Nandemo Nai yo,",
    "artist": "マカロニえんぴつ",
    "lang": "ja",
    "dur": 219,
    "lrcId": 11776559,
    "originalTitle": "なんでもないよ、",
    "nameEn": "It's Nothing,"
  },
  {
    "idx": 15,
    "t": "0:57:48",
    "s": 3468,
    "end": 3750,
    "name": "Shiori",
    "artist": "クリープハイプ",
    "lang": "ja",
    "dur": 260,
    "lrcId": 11364969,
    "originalTitle": "栞",
    "nameEn": "Bookmark"
  },
  {
    "idx": 16,
    "t": "1:02:30",
    "s": 3750,
    "end": 4079,
    "name": "115-Man Kilo no Film",
    "artist": "Official HIGE DANdism",
    "lang": "ja",
    "dur": 325,
    "lrcId": 2521617,
    "originalTitle": "115万キロのフィルム",
    "nameEn": "1.15-Million-Kilometer Film"
  },
  {
    "idx": 17,
    "t": "1:07:59",
    "s": 4079,
    "end": 5724,
    "name": "JANE DOE",
    "artist": "Kenshi Yonezu & Hikaru Utada",
    "lang": "ja",
    "dur": 236,
    "lrcId": 24447415
  },
  {
    "idx": 18,
    "t": "1:35:24",
    "s": 5724,
    "end": 5945,
    "name": "Sukisugite METSU!",
    "artist": "M!LK",
    "lang": "ja",
    "dur": 212,
    "lrcId": 25618259,
    "originalTitle": "好きすぎて滅！",
    "nameEn": "Dying From Love"
  },
  {
    "idx": 19,
    "t": "1:39:05",
    "s": 5945,
    "end": 6223,
    "name": "me me she",
    "artist": "RADWIMPS",
    "lang": "ja",
    "dur": 282,
    "lrcId": 15694390
  },
  {
    "idx": 20,
    "t": "1:43:43",
    "s": 6223,
    "end": 6594,
    "name": "Ashita e no Tegami",
    "artist": "手嶌葵",
    "lang": "ja",
    "dur": 295,
    "lrcId": 14964751,
    "originalTitle": "明日への手紙",
    "nameEn": "A Letter to Tomorrow"
  }
]