{
  "24242930": {
    "8.36": {
      "en": "Say no no to wild ideas",
      "align": {
        "jp": [
          [
            "ぶっ飛んだ",
            0
          ],
          [
            "アイデア",
            3
          ],
          [
            "に",
            2
          ],
          [
            "は",
            2
          ],
          [
            "No No",
            2
          ]
        ],
        "gloss": [
          [
            "ぶっ飛んだ",
            0,
            "wild"
          ],
          [
            "アイデア",
            3,
            "idea"
          ],
          [
            "に",
            2,
            "(dir)"
          ],
          [
            "は",
            2,
            "(top)"
          ],
          [
            "No No",
            2,
            ""
          ]
        ],
        "en": [
          [
            "Say ",
            2
          ],
          [
            "no no ",
            2
          ],
          [
            "to ",
            2
          ],
          [
            "wild ",
            0
          ],
          [
            "ideas",
            3
          ]
        ]
      }
    },
    "10.50": {
      "en": "can't be bothered with that",
      "align": {
        "jp": [
          [
            "なんて",
            4
          ],
          [
            "やって",
            0
          ],
          [
            "られん",
            2
          ],
          [
            "な",
            5
          ]
        ],
        "gloss": [
          [
            "なんて",
            4,
            "things-like"
          ],
          [
            "やって",
            0,
            "do"
          ],
          [
            "られん",
            2,
            "can't"
          ],
          [
            "な",
            5,
            "(emph)"
          ]
        ],
        "en": [
          [
            "can't ",
            2
          ],
          [
            "be ",
            5
          ],
          [
            "bothered ",
            0
          ],
          [
            "with ",
            5
          ],
          [
            "that",
            4
          ]
        ]
      }
    },
    "12.58": {
      "en": "Hey Normie",
      "align": {
        "jp": [
          [
            "Hey ",
            0
          ],
          [
            "Normie",
            2
          ]
        ],
        "gloss": [
          [
            "Hey ",
            0,
            ""
          ],
          [
            "Normie",
            2,
            ""
          ]
        ],
        "en": [
          [
            "Hey ",
            0
          ],
          [
            "Normie",
            2
          ]
        ]
      }
    },
    "13.97": {
      "en": "Hey Normie",
      "align": {
        "jp": [
          [
            "Hey ",
            0
          ],
          [
            "Normie",
            2
          ]
        ],
        "gloss": [
          [
            "Hey ",
            0,
            ""
          ],
          [
            "Normie",
            2,
            ""
          ]
        ],
        "en": [
          [
            "Hey ",
            0
          ],
          [
            "Normie",
            2
          ]
        ]
      }
    },
    "15.74": {
      "en": "Talking big when you're basic? That's lame",
      "align": {
        "jp": [
          [
            "大言",
            0
          ],
          [
            "吐いて",
            0
          ],
          [
            "いた",
            5
          ],
          [
            "って",
            2
          ],
          [
            "平凡",
            4
          ],
          [
            "なんじゃ",
            5
          ],
          [
            "カッコ悪い",
            2
          ],
          [
            "ぜ",
            5
          ]
        ],
        "gloss": [
          [
            "大言",
            0,
            "big-talk"
          ],
          [
            "吐いて",
            0,
            "spout"
          ],
          [
            "いた",
            5,
            "(was)"
          ],
          [
            "って",
            2,
            "(even-if)"
          ],
          [
            "平凡",
            4,
            "ordinary"
          ],
          [
            "なんじゃ",
            5,
            "(if-it-is)"
          ],
          [
            "カッコ悪い",
            2,
            "uncool"
          ],
          [
            "ぜ",
            5,
            "(emph)"
          ]
        ],
        "en": [
          [
            "Talking ",
            0
          ],
          [
            "big ",
            0
          ],
          [
            "when ",
            2
          ],
          [
            "you're ",
            5
          ],
          [
            "basic? ",
            4
          ],
          [
            "That's ",
            5
          ],
          [
            "lame",
            2
          ]
        ]
      }
    },
    "19.92": {
      "en": "Hey Loser",
      "align": {
        "jp": [
          [
            "Hey ",
            0
          ],
          [
            "Looser",
            2
          ]
        ],
        "gloss": [
          [
            "Hey ",
            0,
            ""
          ],
          [
            "Looser",
            2,
            ""
          ]
        ],
        "en": [
          [
            "Hey ",
            0
          ],
          [
            "Loser",
            2
          ]
        ]
      }
    },
    "21.51": {
      "en": "Hey Loser",
      "align": {
        "jp": [
          [
            "Hey ",
            0
          ],
          [
            "Looser",
            2
          ]
        ],
        "gloss": [
          [
            "Hey ",
            0,
            ""
          ],
          [
            "Looser",
            2,
            ""
          ]
        ],
        "en": [
          [
            "Hey ",
            0
          ],
          [
            "Loser",
            2
          ]
        ]
      }
    },
    "23.08": {
      "en": "(Oh No)",
      "align": {
        "jp": [
          [
            "（",
            5
          ],
          [
            "Oh ",
            2
          ],
          [
            "No",
            2
          ],
          [
            "）",
            5
          ]
        ],
        "gloss": [
          [
            "（",
            5,
            ""
          ],
          [
            "Oh ",
            2,
            ""
          ],
          [
            "No",
            2,
            ""
          ],
          [
            "）",
            5,
            ""
          ]
        ],
        "en": [
          [
            "(",
            5
          ],
          [
            "Oh ",
            2
          ],
          [
            "No",
            2
          ],
          [
            ")",
            5
          ]
        ]
      }
    },
    "23.83": {
      "en": "(Easy game, GG)",
      "align": {
        "jp": [
          [
            "（",
            5
          ],
          [
            "イージーゲーム",
            1
          ],
          [
            "　",
            5
          ],
          [
            "GG",
            0
          ],
          [
            "です",
            5
          ],
          [
            "）",
            5
          ]
        ],
        "gloss": [
          [
            "（",
            5,
            ""
          ],
          [
            "イージーゲーム",
            1,
            "easy-game"
          ],
          [
            "　",
            5,
            ""
          ],
          [
            "GG",
            0,
            ""
          ],
          [
            "です",
            5,
            "(is)"
          ],
          [
            "）",
            5,
            ""
          ]
        ],
        "en": [
          [
            "(",
            5
          ],
          [
            "Easy ",
            1
          ],
          [
            "game",
            1
          ],
          [
            ", ",
            5
          ],
          [
            "GG",
            0
          ],
          [
            ")",
            5
          ]
        ]
      }
    },
    "25.57": {
      "en": "just drifting",
      "align": {
        "jp": [
          [
            "ゆるり",
            4
          ],
          [
            "ゆるり",
            4
          ]
        ],
        "gloss": [
          [
            "ゆるり",
            4,
            "(leisurely)"
          ],
          [
            "ゆるり",
            4,
            "(leisurely)"
          ]
        ],
        "en": [
          [
            "just ",
            4
          ],
          [
            "drifting",
            4
          ]
        ]
      }
    },
    "27.58": {
      "en": "(Easy game, GG)",
      "align": {
        "jp": [
          [
            "（",
            5
          ],
          [
            "イージーゲーム",
            1
          ],
          [
            "　",
            5
          ],
          [
            "GG",
            0
          ],
          [
            "です",
            5
          ],
          [
            "）",
            5
          ]
        ],
        "gloss": [
          [
            "（",
            5,
            ""
          ],
          [
            "イージーゲーム",
            1,
            "easy-game"
          ],
          [
            "　",
            5,
            ""
          ],
          [
            "GG",
            0,
            ""
          ],
          [
            "です",
            5,
            "(is)"
          ],
          [
            "）",
            5,
            ""
          ]
        ],
        "en": [
          [
            "(",
            5
          ],
          [
            "Easy ",
            1
          ],
          [
            "game",
            1
          ],
          [
            ", ",
            5
          ],
          [
            "GG",
            0
          ],
          [
            ")",
            5
          ]
        ]
      }
    },
    "29.07": {
      "en": "just letting it slide",
      "align": {
        "jp": [
          [
            "やり過ごし",
            0
          ],
          [
            "て",
            5
          ]
        ],
        "gloss": [
          [
            "やり過ごし",
            0,
            "let-slide"
          ],
          [
            "て",
            5,
            "(and)"
          ]
        ],
        "en": [
          [
            "just ",
            5
          ],
          [
            "letting ",
            5
          ],
          [
            "it ",
            5
          ],
          [
            "slide",
            0
          ]
        ]
      }
    },
    "32.17": {
      "en": "In the half-light — no \"hope,\" no \"love,\" no \"future\"",
      "align": {
        "jp": [
          [
            "「",
            5
          ],
          [
            "期待",
            0
          ],
          [
            "」「",
            5
          ],
          [
            "愛",
            3
          ],
          [
            "」「",
            5
          ],
          [
            "未来",
            1
          ],
          [
            "」",
            5
          ],
          [
            "無い",
            2
          ],
          [
            "薄明かり",
            4
          ],
          [
            "の",
            5
          ],
          [
            "もと",
            4
          ]
        ],
        "gloss": [
          [
            "「",
            5,
            ""
          ],
          [
            "期待",
            0,
            "hope"
          ],
          [
            "」「",
            5,
            ""
          ],
          [
            "愛",
            3,
            "love"
          ],
          [
            "」「",
            5,
            ""
          ],
          [
            "未来",
            1,
            "future"
          ],
          [
            "」",
            5,
            ""
          ],
          [
            "無い",
            2,
            "without"
          ],
          [
            "薄明かり",
            4,
            "twilight"
          ],
          [
            "の",
            5,
            "(attr)"
          ],
          [
            "もと",
            4,
            "under"
          ]
        ],
        "en": [
          [
            "In ",
            5
          ],
          [
            "the ",
            5
          ],
          [
            "half-light ",
            4
          ],
          [
            "— ",
            5
          ],
          [
            "no ",
            2
          ],
          [
            "\"hope,\" ",
            0
          ],
          [
            "no ",
            2
          ],
          [
            "\"love,\" ",
            3
          ],
          [
            "no ",
            2
          ],
          [
            "\"future\"",
            1
          ]
        ]
      }
    },
    "37.25": {
      "en": "Lay Back and Dive",
      "align": {
        "jp": [
          [
            "Lay ",
            1
          ],
          [
            "Back ",
            1
          ],
          [
            "and ",
            1
          ],
          [
            "Dive",
            0
          ]
        ],
        "gloss": [
          [
            "Lay ",
            1,
            ""
          ],
          [
            "Back ",
            1,
            ""
          ],
          [
            "and ",
            1,
            ""
          ],
          [
            "Dive",
            0,
            ""
          ]
        ],
        "en": [
          [
            "Lay ",
            1
          ],
          [
            "Back ",
            1
          ],
          [
            "and ",
            1
          ],
          [
            "Dive",
            0
          ]
        ]
      }
    },
    "40.50": {
      "en": "Through the night",
      "align": {
        "jp": [
          [
            "夜",
            0
          ],
          [
            "の",
            2
          ],
          [
            "間",
            4
          ],
          [
            "に",
            2
          ]
        ],
        "gloss": [
          [
            "夜",
            0,
            "night"
          ],
          [
            "の",
            2,
            "(attr)"
          ],
          [
            "間",
            4,
            "space"
          ],
          [
            "に",
            2,
            "(loc)"
          ]
        ],
        "en": [
          [
            "Through ",
            2
          ],
          [
            "the ",
            4
          ],
          [
            "night",
            0
          ]
        ]
      }
    },
    "44.14": {
      "en": "floating, floating",
      "align": {
        "jp": [
          [
            "ぷかぷか",
            3
          ],
          [
            "ぷか",
            3
          ]
        ],
        "gloss": [
          [
            "ぷかぷか",
            3,
            "(floating)"
          ],
          [
            "ぷか",
            3,
            "(floating)"
          ]
        ],
        "en": [
          [
            "floating",
            3
          ],
          [
            ", ",
            3
          ],
          [
            "floating",
            3
          ]
        ]
      }
    },
    "47.82": {
      "en": "Through the dream",
      "align": {
        "jp": [
          [
            "夢",
            3
          ],
          [
            "の",
            2
          ],
          [
            "間",
            4
          ],
          [
            "に",
            2
          ]
        ],
        "gloss": [
          [
            "夢",
            3,
            "dream"
          ],
          [
            "の",
            2,
            "(attr)"
          ],
          [
            "間",
            4,
            "space"
          ],
          [
            "に",
            2,
            "(loc)"
          ]
        ],
        "en": [
          [
            "Through ",
            2
          ],
          [
            "the ",
            4
          ],
          [
            "dream",
            3
          ]
        ]
      }
    },
    "51.47": {
      "en": "falling headfirst",
      "align": {
        "jp": [
          [
            "真っ逆さま",
            0
          ],
          [
            "だ",
            5
          ]
        ],
        "gloss": [
          [
            "真っ逆さま",
            0,
            "upside-down"
          ],
          [
            "だ",
            5,
            "(is)"
          ]
        ],
        "en": [
          [
            "falling ",
            0
          ],
          [
            "headfirst",
            0
          ]
        ]
      }
    },
    "53.54": {
      "en": "I just — just — just —",
      "align": {
        "jp": [
          [
            "ただ",
            0
          ],
          [
            "　だ",
            5
          ],
          [
            "　だ",
            5
          ],
          [
            "　だ",
            5
          ]
        ],
        "gloss": [
          [
            "ただ",
            0,
            "just"
          ],
          [
            "　だ",
            5,
            "(stutter)"
          ],
          [
            "　だ",
            5,
            "(stutter)"
          ],
          [
            "　だ",
            5,
            "(stutter)"
          ]
        ],
        "en": [
          [
            "I ",
            0
          ],
          [
            "just ",
            0
          ],
          [
            "— ",
            5
          ],
          [
            "just ",
            0
          ],
          [
            "— ",
            5
          ],
          [
            "just ",
            0
          ],
          [
            "—",
            5
          ]
        ]
      }
    },
    "55.64": {
      "en": "wanna dance",
      "align": {
        "jp": [
          [
            "踊って",
            0
          ],
          [
            "いた",
            5
          ]
        ],
        "gloss": [
          [
            "踊って",
            0,
            "dance"
          ],
          [
            "いた",
            5,
            "(was/-ing)"
          ]
        ],
        "en": [
          [
            "wanna ",
            5
          ],
          [
            "dance",
            0
          ]
        ]
      }
    },
    "57.21": {
      "en": "da — an — nce —",
      "align": {
        "jp": [
          [
            "たた",
            0
          ],
          [
            "　た",
            5
          ],
          [
            "　た",
            5
          ]
        ],
        "gloss": [
          [
            "たた",
            0,
            "(stutter)"
          ],
          [
            "　た",
            5,
            "(stutter)"
          ],
          [
            "　た",
            5,
            "(stutter)"
          ]
        ],
        "en": [
          [
            "da ",
            0
          ],
          [
            "— ",
            5
          ],
          [
            "an ",
            0
          ],
          [
            "— ",
            5
          ],
          [
            "nce ",
            0
          ],
          [
            "—",
            5
          ]
        ]
      }
    },
    "58.78": {
      "en": "that's all I want",
      "align": {
        "jp": [
          [
            "たい",
            0
          ],
          [
            "だけ",
            4
          ],
          [
            "なんだ",
            5
          ]
        ],
        "gloss": [
          [
            "たい",
            0,
            "want-to"
          ],
          [
            "だけ",
            4,
            "only"
          ],
          [
            "なんだ",
            5,
            "(it's-that)"
          ]
        ],
        "en": [
          [
            "that's ",
            5
          ],
          [
            "all ",
            4
          ],
          [
            "I ",
            5
          ],
          [
            "want",
            0
          ]
        ]
      }
    },
    "60.86": {
      "en": "I just — just — just —",
      "align": {
        "jp": [
          [
            "ただ",
            0
          ],
          [
            "　だ",
            5
          ],
          [
            "　だ",
            5
          ],
          [
            "　だ",
            5
          ]
        ],
        "gloss": [
          [
            "ただ",
            0,
            "just"
          ],
          [
            "　だ",
            5,
            "(stutter)"
          ],
          [
            "　だ",
            5,
            "(stutter)"
          ],
          [
            "　だ",
            5,
            "(stutter)"
          ]
        ],
        "en": [
          [
            "I ",
            0
          ],
          [
            "just ",
            0
          ],
          [
            "— ",
            5
          ],
          [
            "just ",
            0
          ],
          [
            "— ",
            5
          ],
          [
            "just ",
            0
          ],
          [
            "—",
            5
          ]
        ]
      }
    },
    "62.97": {
      "en": "even if I shut up",
      "align": {
        "jp": [
          [
            "黙って",
            0
          ],
          [
            "いた",
            5
          ],
          [
            "って",
            2
          ]
        ],
        "gloss": [
          [
            "黙って",
            0,
            "shut-up"
          ],
          [
            "いた",
            5,
            "(was)"
          ],
          [
            "って",
            2,
            "(even-if)"
          ]
        ],
        "en": [
          [
            "even ",
            2
          ],
          [
            "if ",
            2
          ],
          [
            "I ",
            5
          ],
          [
            "shut ",
            0
          ],
          [
            "up",
            0
          ]
        ]
      }
    },
    "65.23": {
      "en": "pfft haha",
      "align": {
        "jp": [
          [
            "ぶわ",
            0
          ],
          [
            "っは",
            5
          ]
        ],
        "gloss": [
          [
            "ぶわ",
            0,
            "(pfft)"
          ],
          [
            "っは",
            5,
            "(haha)"
          ]
        ],
        "en": [
          [
            "pfft ",
            0
          ],
          [
            "haha",
            5
          ]
        ]
      }
    },
    "66.23": {
      "en": "Lay Back and Dive",
      "align": {
        "jp": [
          [
            "Lay ",
            1
          ],
          [
            "Back ",
            1
          ],
          [
            "and ",
            1
          ],
          [
            "Dive",
            0
          ]
        ],
        "gloss": [
          [
            "Lay ",
            1,
            ""
          ],
          [
            "Back ",
            1,
            ""
          ],
          [
            "and ",
            1,
            ""
          ],
          [
            "Dive",
            0,
            ""
          ]
        ],
        "en": [
          [
            "Lay ",
            1
          ],
          [
            "Back ",
            1
          ],
          [
            "and ",
            1
          ],
          [
            "Dive",
            0
          ]
        ]
      }
    },
    "68.09": {
      "en": "I'll find something tomorrow, probably",
      "align": {
        "jp": [
          [
            "明日",
            1
          ],
          [
            "に",
            2
          ],
          [
            "は",
            2
          ],
          [
            "きっと",
            5
          ],
          [
            "何か",
            4
          ],
          [
            "見つかん",
            0
          ],
          [
            "だろう",
            5
          ]
        ],
        "gloss": [
          [
            "明日",
            1,
            "tomorrow"
          ],
          [
            "に",
            2,
            "(time)"
          ],
          [
            "は",
            2,
            "(top)"
          ],
          [
            "きっと",
            5,
            "surely"
          ],
          [
            "何か",
            4,
            "something"
          ],
          [
            "見つかん",
            0,
            "be-found"
          ],
          [
            "だろう",
            5,
            "(probably)"
          ]
        ],
        "en": [
          [
            "I'll ",
            5
          ],
          [
            "find ",
            0
          ],
          [
            "something ",
            4
          ],
          [
            "tomorrow",
            1
          ],
          [
            ", ",
            2
          ],
          [
            "probably",
            5
          ]
        ]
      }
    },
    "71.81": {
      "en": "Think I thought the same thing yesterday, huh",
      "align": {
        "jp": [
          [
            "昨日",
            1
          ],
          [
            "も",
            2
          ],
          [
            "そんな",
            4
          ],
          [
            "こと",
            4
          ],
          [
            "思ってた",
            0
          ],
          [
            "っけ",
            5
          ],
          [
            "な",
            5
          ]
        ],
        "gloss": [
          [
            "昨日",
            1,
            "yesterday"
          ],
          [
            "も",
            2,
            "also"
          ],
          [
            "そんな",
            4,
            "that-kind"
          ],
          [
            "こと",
            4,
            "thing"
          ],
          [
            "思ってた",
            0,
            "was-thinking"
          ],
          [
            "っけ",
            5,
            "(wasn't-it?)"
          ],
          [
            "な",
            5,
            "(soft)"
          ]
        ],
        "en": [
          [
            "Think ",
            5
          ],
          [
            "I ",
            5
          ],
          [
            "thought ",
            0
          ],
          [
            "the ",
            5
          ],
          [
            "same ",
            2
          ],
          [
            "thing ",
            4
          ],
          [
            "yesterday",
            1
          ],
          [
            ", ",
            5
          ],
          [
            "huh",
            5
          ]
        ]
      }
    },
    "75.12": {
      "en": "(Peaky, PP)",
      "align": {
        "jp": [
          [
            "（",
            5
          ],
          [
            "ピーキー",
            1
          ],
          [
            "で",
            5
          ],
          [
            "　",
            5
          ],
          [
            "PP",
            0
          ],
          [
            "です",
            5
          ],
          [
            "）",
            5
          ]
        ],
        "gloss": [
          [
            "（",
            5,
            ""
          ],
          [
            "ピーキー",
            1,
            "peaky"
          ],
          [
            "で",
            5,
            "(being)"
          ],
          [
            "　",
            5,
            ""
          ],
          [
            "PP",
            0,
            ""
          ],
          [
            "です",
            5,
            "(is)"
          ],
          [
            "）",
            5,
            ""
          ]
        ],
        "en": [
          [
            "(",
            5
          ],
          [
            "Peaky",
            1
          ],
          [
            ", ",
            5
          ],
          [
            "PP",
            0
          ],
          [
            ")",
            5
          ]
        ]
      }
    },
    "76.93": {
      "en": "drifting around",
      "align": {
        "jp": [
          [
            "のらり",
            4
          ],
          [
            "くらり",
            4
          ]
        ],
        "gloss": [
          [
            "のらり",
            4,
            "(evasive)"
          ],
          [
            "くらり",
            4,
            "(evasive)"
          ]
        ],
        "en": [
          [
            "drifting ",
            4
          ],
          [
            "around",
            4
          ]
        ]
      }
    },
    "78.71": {
      "en": "(Peaky, PP)",
      "align": {
        "jp": [
          [
            "（",
            5
          ],
          [
            "ピーキー",
            1
          ],
          [
            "で",
            5
          ],
          [
            "　",
            5
          ],
          [
            "PP",
            0
          ],
          [
            "です",
            5
          ],
          [
            "）",
            5
          ]
        ],
        "gloss": [
          [
            "（",
            5,
            ""
          ],
          [
            "ピーキー",
            1,
            "peaky"
          ],
          [
            "で",
            5,
            "(being)"
          ],
          [
            "　",
            5,
            ""
          ],
          [
            "PP",
            0,
            ""
          ],
          [
            "です",
            5,
            "(is)"
          ],
          [
            "）",
            5,
            ""
          ]
        ],
        "en": [
          [
            "(",
            5
          ],
          [
            "Peaky",
            1
          ],
          [
            ", ",
            5
          ],
          [
            "PP",
            0
          ],
          [
            ")",
            5
          ]
        ]
      }
    },
    "80.39": {
      "en": "swaying like a wave",
      "align": {
        "jp": [
          [
            "たゆたう",
            3
          ],
          [
            "ように",
            4
          ]
        ],
        "gloss": [
          [
            "たゆたう",
            3,
            "sway"
          ],
          [
            "ように",
            4,
            "like"
          ]
        ],
        "en": [
          [
            "swaying ",
            3
          ],
          [
            "like ",
            4
          ],
          [
            "a ",
            4
          ],
          [
            "wave",
            3
          ]
        ]
      }
    },
    "83.56": {
      "en": "Think too much, you'll end up dumb",
      "align": {
        "jp": [
          [
            "考え",
            4
          ],
          [
            "すぎ",
            4
          ],
          [
            "て",
            5
          ],
          [
            "馬鹿",
            2
          ],
          [
            "に",
            2
          ],
          [
            "だって",
            2
          ],
          [
            "なる",
            0
          ],
          [
            "でしょう",
            5
          ]
        ],
        "gloss": [
          [
            "考え",
            4,
            "think"
          ],
          [
            "すぎ",
            4,
            "too-much"
          ],
          [
            "て",
            5,
            "(and)"
          ],
          [
            "馬鹿",
            2,
            "idiot"
          ],
          [
            "に",
            2,
            "(become-tgt)"
          ],
          [
            "だって",
            2,
            "even"
          ],
          [
            "なる",
            0,
            "become"
          ],
          [
            "でしょう",
            5,
            "(probably)"
          ]
        ],
        "en": [
          [
            "Think ",
            4
          ],
          [
            "too ",
            4
          ],
          [
            "much",
            4
          ],
          [
            ", ",
            5
          ],
          [
            "you'll ",
            5
          ],
          [
            "end ",
            0
          ],
          [
            "up ",
            0
          ],
          [
            "dumb",
            2
          ]
        ]
      }
    },
    "88.60": {
      "en": "Lay Back and Dive",
      "align": {
        "jp": [
          [
            "Lay ",
            1
          ],
          [
            "Back ",
            1
          ],
          [
            "and ",
            1
          ],
          [
            "Dive",
            0
          ]
        ],
        "gloss": [
          [
            "Lay ",
            1,
            ""
          ],
          [
            "Back ",
            1,
            ""
          ],
          [
            "and ",
            1,
            ""
          ],
          [
            "Dive",
            0,
            ""
          ]
        ],
        "en": [
          [
            "Lay ",
            1
          ],
          [
            "Back ",
            1
          ],
          [
            "and ",
            1
          ],
          [
            "Dive",
            0
          ]
        ]
      }
    },
    "91.81": {
      "en": "Through the night",
      "align": {
        "jp": [
          [
            "夜",
            0
          ],
          [
            "の",
            2
          ],
          [
            "間",
            4
          ],
          [
            "に",
            2
          ]
        ],
        "gloss": [
          [
            "夜",
            0,
            "night"
          ],
          [
            "の",
            2,
            "(attr)"
          ],
          [
            "間",
            4,
            "space"
          ],
          [
            "に",
            2,
            "(loc)"
          ]
        ],
        "en": [
          [
            "Through ",
            2
          ],
          [
            "the ",
            4
          ],
          [
            "night",
            0
          ]
        ]
      }
    },
    "95.45": {
      "en": "floating, floating",
      "align": {
        "jp": [
          [
            "ぷかぷか",
            3
          ],
          [
            "ぷか",
            3
          ]
        ],
        "gloss": [
          [
            "ぷかぷか",
            3,
            "(floating)"
          ],
          [
            "ぷか",
            3,
            "(floating)"
          ]
        ],
        "en": [
          [
            "floating",
            3
          ],
          [
            ", ",
            3
          ],
          [
            "floating",
            3
          ]
        ]
      }
    },
    "99.12": {
      "en": "Through the dream",
      "align": {
        "jp": [
          [
            "夢",
            3
          ],
          [
            "の",
            2
          ],
          [
            "間",
            4
          ],
          [
            "に",
            2
          ]
        ],
        "gloss": [
          [
            "夢",
            3,
            "dream"
          ],
          [
            "の",
            2,
            "(attr)"
          ],
          [
            "間",
            4,
            "space"
          ],
          [
            "に",
            2,
            "(loc)"
          ]
        ],
        "en": [
          [
            "Through ",
            2
          ],
          [
            "the ",
            4
          ],
          [
            "dream",
            3
          ]
        ]
      }
    },
    "102.76": {
      "en": "falling headfirst",
      "align": {
        "jp": [
          [
            "真っ逆さま",
            0
          ],
          [
            "だ",
            5
          ]
        ],
        "gloss": [
          [
            "真っ逆さま",
            0,
            "upside-down"
          ],
          [
            "だ",
            5,
            "(is)"
          ]
        ],
        "en": [
          [
            "falling ",
            0
          ],
          [
            "headfirst",
            0
          ]
        ]
      }
    },
    "117.90": {
      "en": "Lay Back and Dive",
      "align": {
        "jp": [
          [
            "Lay ",
            1
          ],
          [
            "Back ",
            1
          ],
          [
            "and ",
            1
          ],
          [
            "Dive",
            0
          ]
        ],
        "gloss": [
          [
            "Lay ",
            1,
            ""
          ],
          [
            "Back ",
            1,
            ""
          ],
          [
            "and ",
            1,
            ""
          ],
          [
            "Dive",
            0,
            ""
          ]
        ],
        "en": [
          [
            "Lay ",
            1
          ],
          [
            "Back ",
            1
          ],
          [
            "and ",
            1
          ],
          [
            "Dive",
            0
          ]
        ]
      }
    },
    "121.10": {
      "en": "Through the night",
      "align": {
        "jp": [
          [
            "夜",
            0
          ],
          [
            "の",
            2
          ],
          [
            "間",
            4
          ],
          [
            "に",
            2
          ]
        ],
        "gloss": [
          [
            "夜",
            0,
            "night"
          ],
          [
            "の",
            2,
            "(attr)"
          ],
          [
            "間",
            4,
            "space"
          ],
          [
            "に",
            2,
            "(loc)"
          ]
        ],
        "en": [
          [
            "Through ",
            2
          ],
          [
            "the ",
            4
          ],
          [
            "night",
            0
          ]
        ]
      }
    },
    "124.79": {
      "en": "floating, floating",
      "align": {
        "jp": [
          [
            "ぷかぷか",
            3
          ],
          [
            "ぷか",
            3
          ]
        ],
        "gloss": [
          [
            "ぷかぷか",
            3,
            "(floating)"
          ],
          [
            "ぷか",
            3,
            "(floating)"
          ]
        ],
        "en": [
          [
            "floating",
            3
          ],
          [
            ", ",
            3
          ],
          [
            "floating",
            3
          ]
        ]
      }
    },
    "128.43": {
      "en": "Through the dream",
      "align": {
        "jp": [
          [
            "夢",
            3
          ],
          [
            "の",
            2
          ],
          [
            "間",
            4
          ],
          [
            "に",
            2
          ]
        ],
        "gloss": [
          [
            "夢",
            3,
            "dream"
          ],
          [
            "の",
            2,
            "(attr)"
          ],
          [
            "間",
            4,
            "space"
          ],
          [
            "に",
            2,
            "(loc)"
          ]
        ],
        "en": [
          [
            "Through ",
            2
          ],
          [
            "the ",
            4
          ],
          [
            "dream",
            3
          ]
        ]
      }
    },
    "132.09": {
      "en": "falling headfirst",
      "align": {
        "jp": [
          [
            "真っ逆さま",
            0
          ],
          [
            "だ",
            5
          ]
        ],
        "gloss": [
          [
            "真っ逆さま",
            0,
            "upside-down"
          ],
          [
            "だ",
            5,
            "(is)"
          ]
        ],
        "en": [
          [
            "falling ",
            0
          ],
          [
            "headfirst",
            0
          ]
        ]
      }
    },
    "134.13": {
      "en": "I just — just — just —",
      "align": {
        "jp": [
          [
            "ただ",
            0
          ],
          [
            "　だ",
            5
          ],
          [
            "　だ",
            5
          ],
          [
            "　だ",
            5
          ]
        ],
        "gloss": [
          [
            "ただ",
            0,
            "just"
          ],
          [
            "　だ",
            5,
            "(stutter)"
          ],
          [
            "　だ",
            5,
            "(stutter)"
          ],
          [
            "　だ",
            5,
            "(stutter)"
          ]
        ],
        "en": [
          [
            "I ",
            0
          ],
          [
            "just ",
            0
          ],
          [
            "— ",
            5
          ],
          [
            "just ",
            0
          ],
          [
            "— ",
            5
          ],
          [
            "just ",
            0
          ],
          [
            "—",
            5
          ]
        ]
      }
    },
    "136.25": {
      "en": "wanna dance",
      "align": {
        "jp": [
          [
            "踊って",
            0
          ],
          [
            "いた",
            5
          ]
        ],
        "gloss": [
          [
            "踊って",
            0,
            "dance"
          ],
          [
            "いた",
            5,
            "(was/-ing)"
          ]
        ],
        "en": [
          [
            "wanna ",
            5
          ],
          [
            "dance",
            0
          ]
        ]
      }
    },
    "137.81": {
      "en": "da — an — nce —",
      "align": {
        "jp": [
          [
            "たた",
            0
          ],
          [
            "　た",
            5
          ],
          [
            "　た",
            5
          ]
        ],
        "gloss": [
          [
            "たた",
            0,
            "(stutter)"
          ],
          [
            "　た",
            5,
            "(stutter)"
          ],
          [
            "　た",
            5,
            "(stutter)"
          ]
        ],
        "en": [
          [
            "da ",
            0
          ],
          [
            "— ",
            5
          ],
          [
            "an ",
            0
          ],
          [
            "— ",
            5
          ],
          [
            "nce ",
            0
          ],
          [
            "—",
            5
          ]
        ]
      }
    },
    "139.40": {
      "en": "that's all I want",
      "align": {
        "jp": [
          [
            "たい",
            0
          ],
          [
            "だけ",
            4
          ],
          [
            "なんだ",
            5
          ]
        ],
        "gloss": [
          [
            "たい",
            0,
            "want-to"
          ],
          [
            "だけ",
            4,
            "only"
          ],
          [
            "なんだ",
            5,
            "(it's-that)"
          ]
        ],
        "en": [
          [
            "that's ",
            5
          ],
          [
            "all ",
            4
          ],
          [
            "I ",
            5
          ],
          [
            "want",
            0
          ]
        ]
      }
    },
    "141.50": {
      "en": "I just — just — just —",
      "align": {
        "jp": [
          [
            "ただ",
            0
          ],
          [
            "　だ",
            5
          ],
          [
            "　だ",
            5
          ],
          [
            "　だ",
            5
          ]
        ],
        "gloss": [
          [
            "ただ",
            0,
            "just"
          ],
          [
            "　だ",
            5,
            "(stutter)"
          ],
          [
            "　だ",
            5,
            "(stutter)"
          ],
          [
            "　だ",
            5,
            "(stutter)"
          ]
        ],
        "en": [
          [
            "I ",
            0
          ],
          [
            "just ",
            0
          ],
          [
            "— ",
            5
          ],
          [
            "just ",
            0
          ],
          [
            "— ",
            5
          ],
          [
            "just ",
            0
          ],
          [
            "—",
            5
          ]
        ]
      }
    },
    "143.58": {
      "en": "even if I shut up",
      "align": {
        "jp": [
          [
            "黙って",
            0
          ],
          [
            "いた",
            5
          ],
          [
            "って",
            2
          ]
        ],
        "gloss": [
          [
            "黙って",
            0,
            "shut-up"
          ],
          [
            "いた",
            5,
            "(was)"
          ],
          [
            "って",
            2,
            "(even-if)"
          ]
        ],
        "en": [
          [
            "even ",
            2
          ],
          [
            "if ",
            2
          ],
          [
            "I ",
            5
          ],
          [
            "shut ",
            0
          ],
          [
            "up",
            0
          ]
        ]
      }
    },
    "145.84": {
      "en": "pfft haha",
      "align": {
        "jp": [
          [
            "ぶわ",
            0
          ],
          [
            "っは",
            5
          ]
        ],
        "gloss": [
          [
            "ぶわ",
            0,
            "(pfft)"
          ],
          [
            "っは",
            5,
            "(haha)"
          ]
        ],
        "en": [
          [
            "pfft ",
            0
          ],
          [
            "haha",
            5
          ]
        ]
      }
    },
    "146.87": {
      "en": "Lay Back and Dive",
      "align": {
        "jp": [
          [
            "Lay ",
            1
          ],
          [
            "Back ",
            1
          ],
          [
            "and ",
            1
          ],
          [
            "Dive",
            0
          ]
        ],
        "gloss": [
          [
            "Lay ",
            1,
            ""
          ],
          [
            "Back ",
            1,
            ""
          ],
          [
            "and ",
            1,
            ""
          ],
          [
            "Dive",
            0,
            ""
          ]
        ],
        "en": [
          [
            "Lay ",
            1
          ],
          [
            "Back ",
            1
          ],
          [
            "and ",
            1
          ],
          [
            "Dive",
            0
          ]
        ]
      }
    }
  }
}